videojedi/JEDi.py
videojedi/V_JEPA.py
videojedi/V_JEPA_utils.py
videojedi/__init__.py
videojedi/mmd_polynomial.py
videojedi/utils.py
videojedi-1.1.0.dist-info/LICENSE.txt
videojedi-1.1.0.dist-info/METADATA
videojedi-1.1.0.dist-info/WHEEL
videojedi-1.1.0.dist-info/RECORD
