Metadata-Version: 2.1
Name: videojedi
Version: 1.1.0
Summary: JEPA Embedding Distance - for video distribution quality assessment.
License: Apache-2.0
Author: oooolga
Author-email: olga.xu823@gmail.com
Requires-Python: >=3.9,<4.0
Classifier: License :: OSI Approved :: Apache Software License
Classifier: Programming Language :: Python :: 3
Classifier: Programming Language :: Python :: 3.9
Classifier: Programming Language :: Python :: 3.10
Classifier: Programming Language :: Python :: 3.11
Classifier: Programming Language :: Python :: 3.12
Classifier: Programming Language :: Python :: 3.13
Requires-Dist: av (>=12.1.0,<13.0.0)
Requires-Dist: scikit-learn (>=1.5.0,<2.0.0)
Requires-Dist: vjepa (==0.1.2)
